lib/test.cpython-39-x86_64-linux-gnu.so
mylibq23452352345-0.0.1.dist-info/METADATA
mylibq23452352345-0.0.1.dist-info/RECORD
mylibq23452352345-0.0.1.dist-info/top_level.txt
mylibq23452352345-0.0.1.dist-info/WHEEL
