Metadata-Version: 2.1
Name: mylibq23452352345
Version: 0.0.1
Summary: Some description here
Home-page: UNKNOWN
Author: Ron Cheong
License: UNKNOWN
Platform: UNKNOWN
Requires-Dist: numpy (>=1.19.2)
Requires-Dist: PyObjC ; platform_system == "Darwin"
Requires-Dist: PyGObject ; platform_system == "Linux"
